consumetpy/__init__.py
consumetpy/consumetapi.py
consumetpy-0.1.2.dist-info/LICENSE
consumetpy-0.1.2.dist-info/METADATA
consumetpy-0.1.2.dist-info/WHEEL
consumetpy-0.1.2.dist-info/top_level.txt
consumetpy-0.1.2.dist-info/RECORD
