Metadata-Version: 2.1
Name: consumetpy
Version: 0.1.2
Summary: A wrapper for the Consumet API
Home-page: https://github.com/notjawad/consumet-py
Author: Jawad
Author-email: evrynoiseatonce@gmail.com
License: UNKNOWN
Platform: UNKNOWN
Classifier: Programming Language :: Python :: 3
Classifier: License :: OSI Approved :: MIT License
Classifier: Operating System :: OS Independent
Requires-Python: >=3.6
License-File: LICENSE
Requires-Dist: requests
